doppkit/__init__.py
doppkit/app.py
doppkit/cache.py
doppkit/grid.py
doppkit/upload.py
doppkit/util.py
doppkit/cli/__init__.py
doppkit/cli/__main__.py
doppkit/cli/cache.py
doppkit/cli/list.py
doppkit/cli/sync.py
doppkit/gui/ExportView.py
doppkit/gui/LogWidget.py
doppkit/gui/MagicLinkDialog.py
doppkit/gui/MenuBar.py
doppkit/gui/SettingsDialog.py
doppkit/gui/UploadView.py
doppkit/gui/__init__.py
doppkit/gui/__main__.py
doppkit/gui/cache.py
doppkit/gui/window.py
doppkit/gui/resources/__init__.py
doppkit-0.4.2.dist-info/licenses/LICENSE
doppkit-0.4.2.dist-info/METADATA
doppkit-0.4.2.dist-info/WHEEL
doppkit-0.4.2.dist-info/entry_points.txt
doppkit-0.4.2.dist-info/top_level.txt
doppkit-0.4.2.dist-info/RECORD
