Metadata-Version: 2.4
Name: doppkit
Version: 0.4.2
Summary: Tool to allow retrival of USACE GRiD data
Maintainer-email: Ognyan Moore <ogi@hobu.co>, Howard Butler <howard@hobu.co>
License:                                  Apache License
Project-URL: homepage, https://github.com/hobuinc/doppkit
Project-URL: repository, https://github.com/hobuinc/doppkit
Classifier: Development Status :: 4 - Beta
Classifier: Intended Audience :: Information Technology
Classifier: Intended Audience :: Science/Research
Classifier: License :: OSI Approved :: Apache Software License
Classifier: Topic :: Scientific/Engineering :: GIS
Requires-Python: >=3.9
License-File: LICENSE
Requires-Dist: httpx
Requires-Dist: rich
Requires-Dist: click
Requires-Dist: aiofiles
Provides-Extra: gui
Requires-Dist: qtpy; extra == "gui"
Requires-Dist: PySide6-essentials~=6.6.0; extra == "gui"
Requires-Dist: qasync; extra == "gui"
Dynamic: license-file
